lifted_pddl/__init__.py
lifted_pddl/__main__.py
lifted_pddl/parser.py
lifted_pddl/data/blocksworld-domain.pddl
lifted_pddl/data/blocksworld-empty-goal.pddl
lifted_pddl/data/blocksworld-problem.pddl
lifted_pddl/data/logistics-domain-exists.pddl
lifted_pddl/data/logistics-domain.pddl
lifted_pddl/data/logistics-problem.pddl
lifted_pddl/data/sokoban-domain-no-clear.pddl
lifted_pddl/data/sokoban-problem.pddl
lifted_pddl-1.2.7.dist-info/licenses/LICENSE
lifted_pddl-1.2.7.dist-info/METADATA
lifted_pddl-1.2.7.dist-info/WHEEL
lifted_pddl-1.2.7.dist-info/entry_points.txt
lifted_pddl-1.2.7.dist-info/top_level.txt
lifted_pddl-1.2.7.dist-info/RECORD
