Metadata-Version: 2.4
Name: lifted-pddl
Version: 1.2.7
Summary: A lightweight framework for parsing PDDL in lifted form.
Home-page: https://github.com/AI-Planning/lifted-pddl
Author: Carlos Núñez Molina
Author-email: ccaarlos@ugr.es
License: MIT
Keywords: automated_planning PDDL parser
Classifier: License :: OSI Approved :: MIT License
Classifier: Programming Language :: Python
Classifier: Programming Language :: Python :: 3
License-File: LICENSE
Requires-Dist: tarski
Dynamic: author
Dynamic: author-email
Dynamic: classifier
Dynamic: description
Dynamic: description-content-type
Dynamic: home-page
Dynamic: keywords
Dynamic: license
Dynamic: license-file
Dynamic: requires-dist
Dynamic: summary
